zarpaint/__init__.py
zarpaint/_add_3d_points.py
zarpaint/_copy_data.py
zarpaint/_dims_chooser.py
zarpaint/_normalize.py
zarpaint/_points_util.py
zarpaint/_version.py
zarpaint/_watershed.py
zarpaint/_zarpaint.py
zarpaint/napari.yaml
zarpaint/reader.py
zarpaint/_tests/__init__.py
zarpaint/_tests/test_copy_data.py
zarpaint/_tests/test_dock_widget.py
zarpaint/_tests/test_reader.py
zarpaint/_tests/test_watershed.py
zarpaint/_tests/test_zarpaint.py
zarpaint-0.4.0.dist-info/LICENSE
zarpaint-0.4.0.dist-info/METADATA
zarpaint-0.4.0.dist-info/WHEEL
zarpaint-0.4.0.dist-info/entry_points.txt
zarpaint-0.4.0.dist-info/top_level.txt
zarpaint-0.4.0.dist-info/RECORD
