Metadata-Version: 2.1
Name: zarpaint
Version: 0.4.0
Summary: Paint segmentations directly to on-disk/remote zarr arrays
Home-page: https://github.com/jni/zarpaint
Author: Abigail S McGovern and Juan Nunez-Iglesias
Author-email: juan.nunez-iglesias@monash.edu
License: BSD-3
Classifier: Development Status :: 4 - Beta
Classifier: Intended Audience :: Developers
Classifier: Framework :: napari
Classifier: Topic :: Software Development :: Testing
Classifier: Programming Language :: Python
Classifier: Programming Language :: Python :: 3
Classifier: Programming Language :: Python :: 3.9
Classifier: Programming Language :: Python :: 3.10
Classifier: Programming Language :: Python :: 3.11
Classifier: Programming Language :: Python :: 3.12
Classifier: Operating System :: OS Independent
Classifier: License :: OSI Approved :: BSD License
Requires-Python: >=3.7
License-File: LICENSE
Requires-Dist: magicgui
Requires-Dist: napari >=0.4.19
Requires-Dist: numpy
Requires-Dist: pyyaml
Requires-Dist: qtpy
Requires-Dist: scipy
Requires-Dist: scikit-image >=0.21
Requires-Dist: toolz
Requires-Dist: zarr <3,>=2.11
Provides-Extra: all
Requires-Dist: tensorstore ; extra == 'all'
Provides-Extra: testing
Requires-Dist: coverage ; extra == 'testing'
Requires-Dist: pytest ; extra == 'testing'
Requires-Dist: pytest-cov ; extra == 'testing'
Requires-Dist: pytest-qt ; extra == 'testing'
Requires-Dist: napari[pyqt5] ; extra == 'testing'
